urllib3/__init__.py
urllib3/_base_connection.py
urllib3/_collections.py
urllib3/_request_methods.py
urllib3/_version.py
urllib3/connection.py
urllib3/connectionpool.py
urllib3/exceptions.py
urllib3/fields.py
urllib3/filepost.py
urllib3/poolmanager.py
urllib3/py.typed
urllib3/response.py
urllib3/contrib/__init__.py
urllib3/contrib/pyopenssl.py
urllib3/contrib/securetransport.py
urllib3/contrib/socks.py
urllib3/contrib/_securetransport/__init__.py
urllib3/contrib/_securetransport/bindings.py
urllib3/contrib/_securetransport/low_level.py
urllib3/util/__init__.py
urllib3/util/connection.py
urllib3/util/proxy.py
urllib3/util/request.py
urllib3/util/response.py
urllib3/util/retry.py
urllib3/util/ssl_.py
urllib3/util/ssl_match_hostname.py
urllib3/util/ssltransport.py
urllib3/util/timeout.py
urllib3/util/url.py
urllib3/util/util.py
urllib3/util/wait.py
urllib3_lts_py37-2025.66471.3.dist-info/licenses/LICENSE.txt
urllib3_lts_py37-2025.66471.3.dist-info/METADATA
urllib3_lts_py37-2025.66471.3.dist-info/WHEEL
urllib3_lts_py37-2025.66471.3.dist-info/top_level.txt
urllib3_lts_py37-2025.66471.3.dist-info/RECORD
